propertiesCaCl2/__init__.py
propertiesCaCl2/functions.py
propertiesCaCl2-0.1.2.dist-info/LICENSE.txt
propertiesCaCl2-0.1.2.dist-info/METADATA
propertiesCaCl2-0.1.2.dist-info/WHEEL
propertiesCaCl2-0.1.2.dist-info/top_level.txt
propertiesCaCl2-0.1.2.dist-info/RECORD
