Metadata-Version: 2.1
Name: propertiesCaCl2
Version: 0.1.2
Summary: A package for aqueous CaCl2 properties calculations
Home-page: UNKNOWN
Author: Dorian Höffner
Author-email: dorian.hoeffner@tu-berlin.de
License: UNKNOWN
Platform: UNKNOWN
Classifier: Programming Language :: Python :: 3
Classifier: License :: OSI Approved :: MIT License
Classifier: Operating System :: OS Independent
Requires-Python: >=3.6
License-File: LICENSE.txt
Requires-Dist: numpy
Requires-Dist: matplotlib
Requires-Dist: pyXSteam
